aiopegelonline/__init__.py
aiopegelonline/const.py
aiopegelonline/exceptions.py
aiopegelonline/models.py
aiopegelonline/py.typed
aiopegelonline-0.1.0.dist-info/LICENSE
aiopegelonline-0.1.0.dist-info/METADATA
aiopegelonline-0.1.0.dist-info/WHEEL
aiopegelonline-0.1.0.dist-info/top_level.txt
aiopegelonline-0.1.0.dist-info/RECORD
