Metadata-Version: 2.1
Name: aiopegelonline
Version: 0.1.0
Summary: Asynchronous library to retrieve data from PEGELONLINE.
Author: mib1185
License: Apache-2.0
Project-URL: homepage, https://github.com/mib1185/aiopegelonline
Project-URL: repository, https://github.com/mib1185/aiopegelonline
Platform: any
Classifier: Intended Audience :: Developers
Classifier: Operating System :: OS Independent
Classifier: Programming Language :: Python
Classifier: Programming Language :: Python :: 3
Classifier: Programming Language :: Python :: 3.9
Classifier: Programming Language :: Python :: 3.10
Classifier: Programming Language :: Python :: 3.11
Classifier: Programming Language :: Python :: 3.12
Classifier: Programming Language :: Python :: 3.13
Classifier: Topic :: Software Development :: Libraries :: Python Modules
Requires-Python: >=3.9
License-File: LICENSE
Requires-Dist: aiohttp
